isolationforestonnx/__init__.py
isolationforestonnx/isolation_forest_converter.py
isolation_forest_onnx-4.0.11.dist-info/METADATA
isolation_forest_onnx-4.0.11.dist-info/WHEEL
isolation_forest_onnx-4.0.11.dist-info/top_level.txt
isolation_forest_onnx-4.0.11.dist-info/RECORD
