Metadata-Version: 2.4
Name: isolation-forest-onnx
Version: 4.0.11
Summary: A converter for the LinkedIn Spark/Scala isolation forest model format to ONNX format.
Home-page: https://github.com/linkedin/isolation-forest
Author: James Verbus
Author-email: james.verbus@gmail.com
License: BSD 2-Clause License
Keywords: isolation forest,ONNX
Requires-Python: >=3.9
Requires-Dist: avro_python3==1.9.1
Requires-Dist: numpy==1.26.4
Requires-Dist: onnx==1.17.0
Requires-Dist: onnxruntime==1.18.0
Requires-Dist: protobuf==5.29.5
Provides-Extra: test
Requires-Dist: pytest==8.3.2; extra == "test"
Requires-Dist: coverage==7.6.1; extra == "test"
Provides-Extra: dev
Requires-Dist: wheel==0.46.2; extra == "dev"
Requires-Dist: flake8==7.1.1; extra == "dev"
Requires-Dist: mypy==1.11; extra == "dev"
Requires-Dist: setuptools==78.1.1; extra == "dev"
Requires-Dist: twine==6.2.0; extra == "dev"
